proxmoxng/.gitignore
proxmoxng/__init__.py
proxmoxng/flaskapi.py
proxmoxng/classes/resources.py
proxmoxng/classes/threadResources.py
proxmoxng/models/vms.py
proxmoxng/threads/apiThread.py
proxmoxng/threads/db.py
proxmoxng/threads/faultTolerance.py
proxmoxng-0.1.3.dist-info/METADATA
proxmoxng-0.1.3.dist-info/WHEEL
proxmoxng-0.1.3.dist-info/entry_points.txt
proxmoxng-0.1.3.dist-info/licenses/LICENSE
proxmoxng-0.1.3.dist-info/RECORD
