Metadata-Version: 2.4
Name: proxmoxng
Version: 0.1.3
Summary: Middleware to control Proxmox clusters on tasks about HA and Live Migration
Project-URL: Homepage, https://github.com/iuricarras/python-proxmox
Author-email: Iuri Carrasqueiro <2222059@my.ipleiria.pt>, Rodrigo Gomes <2221455@my.ipleiria.pt>
License: MIT
License-File: LICENSE
Keywords: HA,Live Migration,Proxmox
Classifier: License :: OSI Approved :: MIT License
Classifier: Operating System :: OS Independent
Classifier: Programming Language :: Python :: 3
Requires-Python: >=3.11
Requires-Dist: blinker==1.9.0
Requires-Dist: certifi==2025.1.31
Requires-Dist: cffi==1.17.1
Requires-Dist: charset-normalizer==3.4.1
Requires-Dist: click==8.1.8
Requires-Dist: colorama==0.4.6
Requires-Dist: cryptography==44.0.2
Requires-Dist: fernet==1.0.1
Requires-Dist: flask-cors==5.0.1
Requires-Dist: flask-sqlalchemy==3.1.1
Requires-Dist: flask==3.1.0
Requires-Dist: greenlet==3.2.1
Requires-Dist: idna==3.10
Requires-Dist: itsdangerous==2.2.0
Requires-Dist: jinja2==3.1.6
Requires-Dist: markupsafe==3.0.2
Requires-Dist: netifaces==0.11.0
Requires-Dist: proxmoxer==2.2.0
Requires-Dist: pyaes==1.6.1
Requires-Dist: pycparser==2.22
Requires-Dist: pyopenssl==25.0.0
Requires-Dist: python-dotenv==1.1.0
Requires-Dist: requests==2.32.3
Requires-Dist: sqlalchemy==2.0.40
Requires-Dist: typing-extensions==4.13.2
Requires-Dist: urllib3==2.4.0
Requires-Dist: werkzeug==3.1.3
